whatsauto/__init__.py
whatsauto/__main__.py
whatsauto/base.py
whatsauto/chat.py
whatsauto/document.py
whatsauto/group.py
whatsauto/group_participant.py
whatsauto/location.py
whatsauto/message.py
whatsauto/photo.py
whatsauto/status/__init__.py
whatsauto/sticker.py
whatsauto/user.py
whatsauto/utils/__init__.py
whatsauto/utils/conversation_parser.py
whatsauto/version.py
whatsauto/video.py
whatsauto/whatsauto.py
whatsauto-0.1.0.dist-info/LICENSE
whatsauto-0.1.0.dist-info/WHEEL
whatsauto-0.1.0.dist-info/METADATA
whatsauto-0.1.0.dist-info/RECORD
