Metadata-Version: 2.1
Name: whatsauto
Version: 0.1.0
Summary: 
Author: hexatester
Author-email: revolusi147id@gmail.com
Requires-Python: >=3.7,<4.0
Classifier: Programming Language :: Python :: 3
Classifier: Programming Language :: Python :: 3.7
Classifier: Programming Language :: Python :: 3.8
Requires-Dist: uiautomator2 (>=2.11.0,<3.0.0)
